fedex_tracking_day/__init__.py
fedex_tracking_day/fedex_track.py
fedex_tracking_day-0.0.10.dist-info/LICENSE
fedex_tracking_day-0.0.10.dist-info/METADATA
fedex_tracking_day-0.0.10.dist-info/WHEEL
fedex_tracking_day-0.0.10.dist-info/entry_points.txt
fedex_tracking_day-0.0.10.dist-info/top_level.txt
fedex_tracking_day-0.0.10.dist-info/RECORD
