Metadata-Version: 2.1
Name: fedex-tracking-day
Version: 0.0.10
Summary: A Python library to intereact with the FedEx Tracking API
Home-page: https://github.com/Daylily-Informatics/fedex_tracking_day
Author: John Major
Author-email: john@daylilyinformatics.com
License-File: LICENSE
Requires-Dist: yaml-config-day
Requires-Dist: requests
Requires-Dist: pytz
